setconstant/__init__.py
setconstant/setconstant.py
setconstant-0.1.3.dist-info/LICENSE.txt
setconstant-0.1.3.dist-info/METADATA
setconstant-0.1.3.dist-info/WHEEL
setconstant-0.1.3.dist-info/top_level.txt
setconstant-0.1.3.dist-info/RECORD
