Metadata-Version: 2.1
Name: setconstant
Version: 0.1.3
Summary: A Python package for managing constants effectively.
Home-page: https://github.com/Anuraj-CodeHaven
Author: Anuraj R
Author-email: anurajanu2883@gmail.com
Classifier: Programming Language :: Python :: 3
Classifier: License :: OSI Approved :: MIT License
Classifier: Operating System :: OS Independent
Requires-Python: >=3.6
License-File: LICENSE.txt
